{"code":"success","data":[{"dataName":"css","dataSrc":"css","fileType":"folder","size":"","children":[{"dataName":"comm.css","dataSrc":"css/comm.css","fileType":"file","size":"10KB","children":[]},{"dataName":"component.css","dataSrc":"css/component.css","fileType":"file","size":"6KB","children":[]},{"dataName":"demo.css","dataSrc":"css/demo.css","fileType":"file","size":"4KB","children":[]},{"dataName":"monn.css","dataSrc":"css/monn.css","fileType":"file","size":"14KB","children":[]}]},{"dataName":"gsal.html","dataSrc":"gsal.html","fileType":"file","size":"24KB","children":[]},{"dataName":"gscp.html","dataSrc":"gscp.html","fileType":"file","size":"32KB","children":[]},{"dataName":"gsyw.html","dataSrc":"gsyw.html","fileType":"file","size":"10KB","children":[]},{"dataName":"gywm.html","dataSrc":"gywm.html","fileType":"file","size":"7KB","children":[]},{"dataName":"hzjg.html","dataSrc":"hzjg.html","fileType":"file","size":"15KB","children":[]},{"dataName":"images","dataSrc":"images","fileType":"folder","size":"","children":[{"dataName":"04.png","dataSrc":"images/04.png","fileType":"file","size":"3KB","children":[]},{"dataName":"1.jpg","dataSrc":"images/1.jpg","fileType":"file","size":"60KB","children":[]},{"dataName":"2.jpg","dataSrc":"images/2.jpg","fileType":"file","size":"62KB","children":[]},{"dataName":"3.jpg","dataSrc":"images/3.jpg","fileType":"file","size":"65KB","children":[]},{"dataName":"4.jpg","dataSrc":"images/4.jpg","fileType":"file","size":"35KB","children":[]},{"dataName":"6.jpg","dataSrc":"images/6.jpg","fileType":"file","size":"91KB","children":[]},{"dataName":"al_1.png","dataSrc":"images/al_1.png","fileType":"file","size":"31KB","children":[]},{"dataName":"al_10.png","dataSrc":"images/al_10.png","fileType":"file","size":"512KB","children":[]},{"dataName":"al_2.png","dataSrc":"images/al_2.png","fileType":"file","size":"82KB","children":[]},{"dataName":"al_3.png","dataSrc":"images/al_3.png","fileType":"file","size":"59KB","children":[]},{"dataName":"al_4.png","dataSrc":"images/al_4.png","fileType":"file","size":"30KB","children":[]},{"dataName":"al_5.png","dataSrc":"images/al_5.png","fileType":"file","size":"69KB","children":[]},{"dataName":"al_6.png","dataSrc":"images/al_6.png","fileType":"file","size":"32KB","children":[]},{"dataName":"al_7.png","dataSrc":"images/al_7.png","fileType":"file","size":"79KB","children":[]},{"dataName":"al_8.png","dataSrc":"images/al_8.png","fileType":"file","size":"59KB","children":[]},{"dataName":"al_9.png","dataSrc":"images/al_9.png","fileType":"file","size":"1085KB","children":[]},{"dataName":"banner1.jpg","dataSrc":"images/banner1.jpg","fileType":"file","size":"102KB","children":[]},{"dataName":"banner2.jpg","dataSrc":"images/banner2.jpg","fileType":"file","size":"109KB","children":[]},{"dataName":"banner3.jpg","dataSrc":"images/banner3.jpg","fileType":"file","size":"149KB","children":[]},{"dataName":"banner4.jpg","dataSrc":"images/banner4.jpg","fileType":"file","size":"155KB","children":[]},{"dataName":"bj.png","dataSrc":"images/bj.png","fileType":"file","size":"5KB","children":[]},{"dataName":"cp_1.png","dataSrc":"images/cp_1.png","fileType":"file","size":"144KB","children":[]},{"dataName":"cp_2.png","dataSrc":"images/cp_2.png","fileType":"file","size":"26KB","children":[]},{"dataName":"cp_3.png","dataSrc":"images/cp_3.png","fileType":"file","size":"121KB","children":[]},{"dataName":"cp_4.png","dataSrc":"images/cp_4.png","fileType":"file","size":"46KB","children":[]},{"dataName":"cp_5.png","dataSrc":"images/cp_5.png","fileType":"file","size":"29KB","children":[]},{"dataName":"cp_6.png","dataSrc":"images/cp_6.png","fileType":"file","size":"18KB","children":[]},{"dataName":"cp_7.png","dataSrc":"images/cp_7.png","fileType":"file","size":"40KB","children":[]},{"dataName":"cp_8.png","dataSrc":"images/cp_8.png","fileType":"file","size":"79KB","children":[]},{"dataName":"dzkf.png","dataSrc":"images/dzkf.png","fileType":"file","size":"4KB","children":[]},{"dataName":"ewm_qq.png","dataSrc":"images/ewm_qq.png","fileType":"file","size":"193KB","children":[]},{"dataName":"ewm_wx - 副本.png","dataSrc":"images/ewm_wx - 副本.png","fileType":"file","size":"22KB","children":[]},{"dataName":"ewm_wx.jpg","dataSrc":"images/ewm_wx.jpg","fileType":"file","size":"40KB","children":[]},{"dataName":"ewm_wx.png","dataSrc":"images/ewm_wx.png","fileType":"file","size":"43KB","children":[]},{"dataName":"fabj.png","dataSrc":"images/fabj.png","fileType":"file","size":"28KB","children":[]},{"dataName":"gb.png","dataSrc":"images/gb.png","fileType":"file","size":"1KB","children":[]},{"dataName":"gb_left.png","dataSrc":"images/gb_left.png","fileType":"file","size":"1KB","children":[]},{"dataName":"gb_right.png","dataSrc":"images/gb_right.png","fileType":"file","size":"4KB","children":[]},{"dataName":"gsjj.jpg","dataSrc":"images/gsjj.jpg","fileType":"file","size":"63KB","children":[]},{"dataName":"gyxh.jpg","dataSrc":"images/gyxh.jpg","fileType":"file","size":"86KB","children":[]},{"dataName":"jgbj.png","dataSrc":"images/jgbj.png","fileType":"file","size":"12KB","children":[]},{"dataName":"jgg_bj.png","dataSrc":"images/jgg_bj.png","fileType":"file","size":"20KB","children":[]},{"dataName":"jg_kz.png","dataSrc":"images/jg_kz.png","fileType":"file","size":"5KB","children":[]},{"dataName":"label_1.jpg","dataSrc":"images/label_1.jpg","fileType":"file","size":"53KB","children":[]},{"dataName":"label_2.jpg","dataSrc":"images/label_2.jpg","fileType":"file","size":"53KB","children":[]},{"dataName":"label_3.jpg","dataSrc":"images/label_3.jpg","fileType":"file","size":"49KB","children":[]},{"dataName":"label_4.jpg","dataSrc":"images/label_4.jpg","fileType":"file","size":"50KB","children":[]},{"dataName":"large","dataSrc":"images/large","fileType":"folder","size":"","children":[{"dataName":"al_1.png","dataSrc":"images/large/al_1.png","fileType":"file","size":"154KB","children":[]},{"dataName":"al_2.png","dataSrc":"images/large/al_2.png","fileType":"file","size":"207KB","children":[]},{"dataName":"al_3.png","dataSrc":"images/large/al_3.png","fileType":"file","size":"238KB","children":[]},{"dataName":"al_4.png","dataSrc":"images/large/al_4.png","fileType":"file","size":"141KB","children":[]},{"dataName":"al_5.png","dataSrc":"images/large/al_5.png","fileType":"file","size":"238KB","children":[]},{"dataName":"al_6.png","dataSrc":"images/large/al_6.png","fileType":"file","size":"71KB","children":[]},{"dataName":"al_7.png","dataSrc":"images/large/al_7.png","fileType":"file","size":"85KB","children":[]},{"dataName":"al_8.png","dataSrc":"images/large/al_8.png","fileType":"file","size":"262KB","children":[]},{"dataName":"cp_1.png","dataSrc":"images/large/cp_1.png","fileType":"file","size":"40KB","children":[]},{"dataName":"cp_2.png","dataSrc":"images/large/cp_2.png","fileType":"file","size":"23KB","children":[]},{"dataName":"cp_3.png","dataSrc":"images/large/cp_3.png","fileType":"file","size":"122KB","children":[]},{"dataName":"cp_4.png","dataSrc":"images/large/cp_4.png","fileType":"file","size":"56KB","children":[]},{"dataName":"cp_5.png","dataSrc":"images/large/cp_5.png","fileType":"file","size":"166KB","children":[]},{"dataName":"cp_6.png","dataSrc":"images/large/cp_6.png","fileType":"file","size":"66KB","children":[]},{"dataName":"cp_7.png","dataSrc":"images/large/cp_7.png","fileType":"file","size":"36KB","children":[]},{"dataName":"cp_8.png","dataSrc":"images/large/cp_8.png","fileType":"file","size":"75KB","children":[]}]},{"dataName":"left.png","dataSrc":"images/left.png","fileType":"file","size":"5KB","children":[]},{"dataName":"logo.png","dataSrc":"images/logo.png","fileType":"file","size":"18KB","children":[]},{"dataName":"luq.png","dataSrc":"images/luq.png","fileType":"file","size":"5KB","children":[]},{"dataName":"lxwm.jpg","dataSrc":"images/lxwm.jpg","fileType":"file","size":"93KB","children":[]},{"dataName":"right.png","dataSrc":"images/right.png","fileType":"file","size":"5KB","children":[]},{"dataName":"rjkf.png","dataSrc":"images/rjkf.png","fileType":"file","size":"4KB","children":[]},{"dataName":"syyx.png","dataSrc":"images/syyx.png","fileType":"file","size":"4KB","children":[]},{"dataName":"thumb","dataSrc":"images/thumb","fileType":"folder","size":"","children":[{"dataName":"al_1.png","dataSrc":"images/thumb/al_1.png","fileType":"file","size":"46KB","children":[]},{"dataName":"al_11.png","dataSrc":"images/thumb/al_11.png","fileType":"file","size":"219KB","children":[]},{"dataName":"al_12.png","dataSrc":"images/thumb/al_12.png","fileType":"file","size":"202KB","children":[]},{"dataName":"al_2.png","dataSrc":"images/thumb/al_2.png","fileType":"file","size":"59KB","children":[]},{"dataName":"al_3.png","dataSrc":"images/thumb/al_3.png","fileType":"file","size":"68KB","children":[]},{"dataName":"al_4.png","dataSrc":"images/thumb/al_4.png","fileType":"file","size":"758KB","children":[]},{"dataName":"al_5.png","dataSrc":"images/thumb/al_5.png","fileType":"file","size":"65KB","children":[]},{"dataName":"al_6.png","dataSrc":"images/thumb/al_6.png","fileType":"file","size":"29KB","children":[]},{"dataName":"al_7.png","dataSrc":"images/thumb/al_7.png","fileType":"file","size":"32KB","children":[]},{"dataName":"al_8.png","dataSrc":"images/thumb/al_8.png","fileType":"file","size":"80KB","children":[]},{"dataName":"cp_1.png","dataSrc":"images/thumb/cp_1.png","fileType":"file","size":"16KB","children":[]},{"dataName":"cp_2.png","dataSrc":"images/thumb/cp_2.png","fileType":"file","size":"23KB","children":[]},{"dataName":"cp_3.png","dataSrc":"images/thumb/cp_3.png","fileType":"file","size":"47KB","children":[]},{"dataName":"cp_4.png","dataSrc":"images/thumb/cp_4.png","fileType":"file","size":"20KB","children":[]},{"dataName":"cp_5.png","dataSrc":"images/thumb/cp_5.png","fileType":"file","size":"56KB","children":[]},{"dataName":"cp_6.png","dataSrc":"images/thumb/cp_6.png","fileType":"file","size":"24KB","children":[]},{"dataName":"cp_7.png","dataSrc":"images/thumb/cp_7.png","fileType":"file","size":"15KB","children":[]},{"dataName":"cp_8.png","dataSrc":"images/thumb/cp_8.png","fileType":"file","size":"26KB","children":[]}]},{"dataName":"wzjs.png","dataSrc":"images/wzjs.png","fileType":"file","size":"4KB","children":[]},{"dataName":"xhal.jpg","dataSrc":"images/xhal.jpg","fileType":"file","size":"89KB","children":[]},{"dataName":"xhcp.jpg","dataSrc":"images/xhcp.jpg","fileType":"file","size":"74KB","children":[]},{"dataName":"xhfa.jpg","dataSrc":"images/xhfa.jpg","fileType":"file","size":"66KB","children":[]},{"dataName":"xhgb.png","dataSrc":"images/xhgb.png","fileType":"file","size":"31KB","children":[]},{"dataName":"xhjg.jpg","dataSrc":"images/xhjg.jpg","fileType":"file","size":"86KB","children":[]},{"dataName":"xhkz.png","dataSrc":"images/xhkz.png","fileType":"file","size":"105KB","children":[]},{"dataName":"xhsj.png","dataSrc":"images/xhsj.png","fileType":"file","size":"150KB","children":[]},{"dataName":"xhyw.jpg","dataSrc":"images/xhyw.jpg","fileType":"file","size":"68KB","children":[]},{"dataName":"xtjc.png","dataSrc":"images/xtjc.png","fileType":"file","size":"4KB","children":[]},{"dataName":"ywbj.png","dataSrc":"images/ywbj.png","fileType":"file","size":"37KB","children":[]},{"dataName":"ywtx.png","dataSrc":"images/ywtx.png","fileType":"file","size":"26KB","children":[]},{"dataName":"ywtx_1.png","dataSrc":"images/ywtx_1.png","fileType":"file","size":"27KB","children":[]},{"dataName":"ywtx_10.png","dataSrc":"images/ywtx_10.png","fileType":"file","size":"11KB","children":[]},{"dataName":"ywtx_11.png","dataSrc":"images/ywtx_11.png","fileType":"file","size":"13KB","children":[]},{"dataName":"ywtx_12.png","dataSrc":"images/ywtx_12.png","fileType":"file","size":"21KB","children":[]},{"dataName":"ywtx_2.png","dataSrc":"images/ywtx_2.png","fileType":"file","size":"17KB","children":[]},{"dataName":"ywtx_3.png","dataSrc":"images/ywtx_3.png","fileType":"file","size":"12KB","children":[]},{"dataName":"ywtx_4.png","dataSrc":"images/ywtx_4.png","fileType":"file","size":"11KB","children":[]},{"dataName":"ywtx_5.png","dataSrc":"images/ywtx_5.png","fileType":"file","size":"8KB","children":[]},{"dataName":"ywtx_6.png","dataSrc":"images/ywtx_6.png","fileType":"file","size":"14KB","children":[]},{"dataName":"ywtx_7.png","dataSrc":"images/ywtx_7.png","fileType":"file","size":"14KB","children":[]},{"dataName":"ywtx_8.png","dataSrc":"images/ywtx_8.png","fileType":"file","size":"8KB","children":[]},{"dataName":"ywtx_9.png","dataSrc":"images/ywtx_9.png","fileType":"file","size":"9KB","children":[]}]},{"dataName":"index.html","dataSrc":"index.html","fileType":"file","size":"24KB","children":[]},{"dataName":"jjfa.html","dataSrc":"jjfa.html","fileType":"file","size":"6KB","children":[]},{"dataName":"js","dataSrc":"js","fileType":"folder","size":"","children":[{"dataName":"jquery-1.7.2.min.js","dataSrc":"js/jquery-1.7.2.min.js","fileType":"file","size":"93KB","children":[]},{"dataName":"lunbo.js","dataSrc":"js/lunbo.js","fileType":"file","size":"1KB","children":[]},{"dataName":"sfq.js","dataSrc":"js/sfq.js","fileType":"file","size":"1KB","children":[]}]},{"dataName":"layer","dataSrc":"layer","fileType":"folder","size":"","children":[{"dataName":"layer.js","dataSrc":"layer/layer.js","fileType":"file","size":"21KB","children":[]},{"dataName":"mobile","dataSrc":"layer/mobile","fileType":"folder","size":"","children":[{"dataName":"layer.js","dataSrc":"layer/mobile/layer.js","fileType":"file","size":"4KB","children":[]},{"dataName":"need","dataSrc":"layer/mobile/need","fileType":"folder","size":"","children":[{"dataName":"layer.css","dataSrc":"layer/mobile/need/layer.css","fileType":"file","size":"6KB","children":[]}]}]},{"dataName":"skin","dataSrc":"layer/skin","fileType":"folder","size":"","children":[{"dataName":"default","dataSrc":"layer/skin/default","fileType":"folder","size":"","children":[{"dataName":"icon-ext.png","dataSrc":"layer/skin/default/icon-ext.png","fileType":"file","size":"6KB","children":[]},{"dataName":"icon.png","dataSrc":"layer/skin/default/icon.png","fileType":"file","size":"12KB","children":[]},{"dataName":"layer.css","dataSrc":"layer/skin/default/layer.css","fileType":"file","size":"14KB","children":[]},{"dataName":"loading-0.gif","dataSrc":"layer/skin/default/loading-0.gif","fileType":"file","size":"6KB","children":[]},{"dataName":"loading-1.gif","dataSrc":"layer/skin/default/loading-1.gif","fileType":"file","size":"1KB","children":[]},{"dataName":"loading-2.gif","dataSrc":"layer/skin/default/loading-2.gif","fileType":"file","size":"2KB","children":[]}]}]}]},{"dataName":"_menu.json","dataSrc":"_menu.json","fileType":"file","size":"1KB","children":[]},{"dataName":"about.html","dataSrc":"about.html","fileType":"file","size":"19KB","children":[]},{"dataName":"contact.html","dataSrc":"contact.html","fileType":"file","size":"21KB","children":[]},{"dataName":"css","dataSrc":"css","fileType":"folder","size":"","children":[{"dataName":"bootstrap.css","dataSrc":"css/bootstrap.css","fileType":"file","size":"117KB","children":[]},{"dataName":"style.css","dataSrc":"css/style.css","fileType":"file","size":"107KB","children":[]}]},{"dataName":"images","dataSrc":"images","fileType":"folder","size":"","children":[{"dataName":"beijing.png","dataSrc":"images/beijing.png","fileType":"file","size":"1KB","children":[]},{"dataName":"down_img1.jpg","dataSrc":"images/down_img1.jpg","fileType":"file","size":"251KB","children":[]},{"dataName":"down_img10.png","dataSrc":"images/down_img10.png","fileType":"file","size":"4KB","children":[]},{"dataName":"down_img2.jpg","dataSrc":"images/down_img2.jpg","fileType":"file","size":"12KB","children":[]},{"dataName":"down_img3.png","dataSrc":"images/down_img3.png","fileType":"file","size":"4KB","children":[]},{"dataName":"down_img4.png","dataSrc":"images/down_img4.png","fileType":"file","size":"4KB","children":[]},{"dataName":"down_img5.png","dataSrc":"images/down_img5.png","fileType":"file","size":"4KB","children":[]},{"dataName":"down_img6.png","dataSrc":"images/down_img6.png","fileType":"file","size":"4KB","children":[]},{"dataName":"down_img9.png","dataSrc":"images/down_img9.png","fileType":"file","size":"3KB","children":[]},{"dataName":"imgplayer.png","dataSrc":"images/imgplayer.png","fileType":"file","size":"4KB","children":[]},{"dataName":"join_img5.png","dataSrc":"images/join_img5.png","fileType":"file","size":"3KB","children":[]},{"dataName":"main_img1.png","dataSrc":"images/main_img1.png","fileType":"file","size":"4KB","children":[]},{"dataName":"main_img12.png","dataSrc":"images/main_img12.png","fileType":"file","size":"3KB","children":[]},{"dataName":"main_img13.png","dataSrc":"images/main_img13.png","fileType":"file","size":"3KB","children":[]},{"dataName":"main_img2.png","dataSrc":"images/main_img2.png","fileType":"file","size":"3KB","children":[]},{"dataName":"main_img2_h.png","dataSrc":"images/main_img2_h.png","fileType":"file","size":"3KB","children":[]},{"dataName":"main_img3.jpg","dataSrc":"images/main_img3.jpg","fileType":"file","size":"2KB","children":[]},{"dataName":"main_img4.png","dataSrc":"images/main_img4.png","fileType":"file","size":"4KB","children":[]},{"dataName":"main_img4_h.png","dataSrc":"images/main_img4_h.png","fileType":"file","size":"4KB","children":[]},{"dataName":"main_img5.png","dataSrc":"images/main_img5.png","fileType":"file","size":"4KB","children":[]},{"dataName":"main_img6.png","dataSrc":"images/main_img6.png","fileType":"file","size":"4KB","children":[]},{"dataName":"main_img7_a.png","dataSrc":"images/main_img7_a.png","fileType":"file","size":"14KB","children":[]},{"dataName":"main_img7_c.png","dataSrc":"images/main_img7_c.png","fileType":"file","size":"14KB","children":[]},{"dataName":"main_img7_d.png","dataSrc":"images/main_img7_d.png","fileType":"file","size":"3KB","children":[]},{"dataName":"main_img7_e.jpg","dataSrc":"images/main_img7_e.jpg","fileType":"file","size":"45KB","children":[]},{"dataName":"main_img7_f.jpg","dataSrc":"images/main_img7_f.jpg","fileType":"file","size":"14KB","children":[]},{"dataName":"team_img2.png","dataSrc":"images/team_img2.png","fileType":"file","size":"4KB","children":[]},{"dataName":"team_img9.png","dataSrc":"images/team_img9.png","fileType":"file","size":"4KB","children":[]},{"dataName":"top_img2.png","dataSrc":"images/top_img2.png","fileType":"file","size":"3KB","children":[]}]},{"dataName":"index.html","dataSrc":"index.html","fileType":"file","size":"26KB","children":[]},{"dataName":"js","dataSrc":"js","fileType":"folder","size":"","children":[{"dataName":"ef988ee59aa34e0cb703ebd011030c9e.js","dataSrc":"js/ef988ee59aa34e0cb703ebd011030c9e.js","fileType":"file","size":"1KB","children":[]},{"dataName":"jia.js","dataSrc":"js/jia.js","fileType":"file","size":"23KB","children":[]},{"dataName":"jq.mobi.min.js","dataSrc":"js/jq.mobi.min.js","fileType":"file","size":"21KB","children":[]},{"dataName":"jquery.min.js","dataSrc":"js/jquery.min.js","fileType":"file","size":"93KB","children":[]},{"dataName":"jquery.scrollto.js","dataSrc":"js/jquery.scrollto.js","fileType":"file","size":"8KB","children":[]},{"dataName":"jquery.superslide.2.1.1.js","dataSrc":"js/jquery.superslide.2.1.1.js","fileType":"file","size":"12KB","children":[]},{"dataName":"navslide.js","dataSrc":"js/navslide.js","fileType":"file","size":"1KB","children":[]},{"dataName":"pzinputmsg.js","dataSrc":"js/pzinputmsg.js","fileType":"file","size":"1KB","children":[]},{"dataName":"touchslide.1.1.js","dataSrc":"js/touchslide.1.1.js","fileType":"file","size":"6KB","children":[]}]},{"dataName":"news.html","dataSrc":"news.html","fileType":"file","size":"17KB","children":[]},{"dataName":"newsshow.html","dataSrc":"newsshow.html","fileType":"file","size":"19KB","children":[]},{"dataName":"picture","dataSrc":"picture","fileType":"folder","size":"","children":[{"dataName":"1742141.jpg","dataSrc":"picture/1742141.jpg","fileType":"file","size":"55KB","children":[]},{"dataName":"201511051701588225259.png","dataSrc":"picture/201511051701588225259.png","fileType":"file","size":"84KB","children":[]},{"dataName":"201511171314554568191.jpg","dataSrc":"picture/201511171314554568191.jpg","fileType":"file","size":"16KB","children":[]},{"dataName":"23130375.jpg","dataSrc":"picture/23130375.jpg","fileType":"file","size":"87KB","children":[]},{"dataName":"231303759748851.jpg","dataSrc":"picture/231303759748851.jpg","fileType":"file","size":"45KB","children":[]},{"dataName":"25150721.png","dataSrc":"picture/25150721.png","fileType":"file","size":"77KB","children":[]},{"dataName":"2921012.png","dataSrc":"picture/2921012.png","fileType":"file","size":"126KB","children":[]},{"dataName":"3192654.png","dataSrc":"picture/3192654.png","fileType":"file","size":"50KB","children":[]},{"dataName":"3983766.jpg","dataSrc":"picture/3983766.jpg","fileType":"file","size":"28KB","children":[]},{"dataName":"5047115.png","dataSrc":"picture/5047115.png","fileType":"file","size":"148KB","children":[]},{"dataName":"5229856.png","dataSrc":"picture/5229856.png","fileType":"file","size":"56KB","children":[]},{"dataName":"55892845.png","dataSrc":"picture/55892845.png","fileType":"file","size":"251KB","children":[]},{"dataName":"6358034065306001681703050.jpg","dataSrc":"picture/6358034065306001681703050.jpg","fileType":"file","size":"18KB","children":[]},{"dataName":"6358224600006577481595986.jpg","dataSrc":"picture/6358224600006577481595986.jpg","fileType":"file","size":"13KB","children":[]},{"dataName":"6358336364409006214966780.jpg","dataSrc":"picture/6358336364409006214966780.jpg","fileType":"file","size":"5KB","children":[]},{"dataName":"8499902.png","dataSrc":"picture/8499902.png","fileType":"file","size":"296KB","children":[]},{"dataName":"9553103.png","dataSrc":"picture/9553103.png","fileType":"file","size":"338KB","children":[]},{"dataName":"aa246b77-dfa0-453b-8edb-02bb2f265071.jpg","dataSrc":"picture/aa246b77-dfa0-453b-8edb-02bb2f265071.jpg","fileType":"file","size":"71KB","children":[]},{"dataName":"contact_img8.png","dataSrc":"picture/contact_img8.png","fileType":"file","size":"3KB","children":[]},{"dataName":"contact_img9.png","dataSrc":"picture/contact_img9.png","fileType":"file","size":"3KB","children":[]},{"dataName":"down_img8.png","dataSrc":"picture/down_img8.png","fileType":"file","size":"6KB","children":[]},{"dataName":"join_img2.png","dataSrc":"picture/join_img2.png","fileType":"file","size":"3KB","children":[]},{"dataName":"logo.jpg","dataSrc":"picture/logo.jpg","fileType":"file","size":"27KB","children":[]},{"dataName":"main_img10.png","dataSrc":"picture/main_img10.png","fileType":"file","size":"3KB","children":[]},{"dataName":"main_img11739633628422479.jpg","dataSrc":"picture/main_img11739633628422479.jpg","fileType":"file","size":"48KB","children":[]},{"dataName":"main_img117396362.jpg","dataSrc":"picture/main_img117396362.jpg","fileType":"file","size":"22KB","children":[]},{"dataName":"main_img1173963623479594.jpg","dataSrc":"picture/main_img1173963623479594.jpg","fileType":"file","size":"71KB","children":[]},{"dataName":"main_img157774224.jpg","dataSrc":"picture/main_img157774224.jpg","fileType":"file","size":"29KB","children":[]},{"dataName":"main_img7.png","dataSrc":"picture/main_img7.png","fileType":"file","size":"413KB","children":[]},{"dataName":"main_img7_b.png","dataSrc":"picture/main_img7_b.png","fileType":"file","size":"409KB","children":[]},{"dataName":"new_img18006324.jpg","dataSrc":"picture/new_img18006324.jpg","fileType":"file","size":"64KB","children":[]},{"dataName":"new_img29793906.jpg","dataSrc":"picture/new_img29793906.jpg","fileType":"file","size":"39KB","children":[]},{"dataName":"new_img38774135.jpg","dataSrc":"picture/new_img38774135.jpg","fileType":"file","size":"59KB","children":[]},{"dataName":"rgfwrtgq3t6401681.jpg","dataSrc":"picture/rgfwrtgq3t6401681.jpg","fileType":"file","size":"48KB","children":[]},{"dataName":"top_img4.jpg","dataSrc":"picture/top_img4.jpg","fileType":"file","size":"1KB","children":[]},{"dataName":"top_img5.jpg","dataSrc":"picture/top_img5.jpg","fileType":"file","size":"1KB","children":[]},{"dataName":"top_img64575469.png","dataSrc":"picture/top_img64575469.png","fileType":"file","size":"4KB","children":[]},{"dataName":"top_imgt1.png","dataSrc":"picture/top_imgt1.png","fileType":"file","size":"4KB","children":[]},{"dataName":"top_imgt2.png","dataSrc":"picture/top_imgt2.png","fileType":"file","size":"4KB","children":[]},{"dataName":"top_imgt3.png","dataSrc":"picture/top_imgt3.png","fileType":"file","size":"4KB","children":[]},{"dataName":"top_imgt4.png","dataSrc":"picture/top_imgt4.png","fileType":"file","size":"4KB","children":[]}]},{"dataName":"team.html","dataSrc":"team.html","fileType":"file","size":"27KB","children":[]},{"dataName":"yewu.html","dataSrc":"yewu.html","fileType":"file","size":"23KB","children":[]},{"dataName":"_menu.json","dataSrc":"_menu.json","fileType":"file","size":"1KB","children":[]},{"dataName":"css","dataSrc":"css","fileType":"folder","size":"","children":[]},{"dataName":"images","dataSrc":"images","fileType":"folder","size":"","children":[{"dataName":"bg.jpg","dataSrc":"images/bg.jpg","fileType":"file","size":"7KB","children":[]},{"dataName":"bg3.png","dataSrc":"images/bg3.png","fileType":"file","size":"12KB","children":[]},{"dataName":"ct.jpg","dataSrc":"images/ct.jpg","fileType":"file","size":"48KB","children":[]},{"dataName":"hd.jpg","dataSrc":"images/hd.jpg","fileType":"file","size":"154KB","children":[]},{"dataName":"list.png","dataSrc":"images/list.png","fileType":"file","size":"5KB","children":[]},{"dataName":"md-bg.jpg","dataSrc":"images/md-bg.jpg","fileType":"file","size":"5KB","children":[]},{"dataName":"md-bg2.jpg","dataSrc":"images/md-bg2.jpg","fileType":"file","size":"4KB","children":[]},{"dataName":"nav.png","dataSrc":"images/nav.png","fileType":"file","size":"14KB","children":[]},{"dataName":"pic1.jpg","dataSrc":"images/pic1.jpg","fileType":"file","size":"7KB","children":[]},{"dataName":"pic2.jpg","dataSrc":"images/pic2.jpg","fileType":"file","size":"6KB","children":[]},{"dataName":"pic3.jpg","dataSrc":"images/pic3.jpg","fileType":"file","size":"4KB","children":[]},{"dataName":"rp1.jpg","dataSrc":"images/rp1.jpg","fileType":"file","size":"145KB","children":[]},{"dataName":"rp2.jpg","dataSrc":"images/rp2.jpg","fileType":"file","size":"98KB","children":[]},{"dataName":"sp.png","dataSrc":"images/sp.png","fileType":"file","size":"9KB","children":[]},{"dataName":"tou1.png","dataSrc":"images/tou1.png","fileType":"file","size":"12KB","children":[]},{"dataName":"tou2.png","dataSrc":"images/tou2.png","fileType":"file","size":"11KB","children":[]},{"dataName":"tou3.png","dataSrc":"images/tou3.png","fileType":"file","size":"12KB","children":[]},{"dataName":"tou4.png","dataSrc":"images/tou4.png","fileType":"file","size":"12KB","children":[]},{"dataName":"tou5.png","dataSrc":"images/tou5.png","fileType":"file","size":"12KB","children":[]},{"dataName":"v1.jpg","dataSrc":"images/v1.jpg","fileType":"file","size":"5KB","children":[]},{"dataName":"v10.jpg","dataSrc":"images/v10.jpg","fileType":"file","size":"6KB","children":[]},{"dataName":"v11.jpg","dataSrc":"images/v11.jpg","fileType":"file","size":"7KB","children":[]},{"dataName":"v12.jpg","dataSrc":"images/v12.jpg","fileType":"file","size":"6KB","children":[]},{"dataName":"v13.jpg","dataSrc":"images/v13.jpg","fileType":"file","size":"4KB","children":[]},{"dataName":"v14.jpg","dataSrc":"images/v14.jpg","fileType":"file","size":"5KB","children":[]},{"dataName":"v15.jpg","dataSrc":"images/v15.jpg","fileType":"file","size":"5KB","children":[]},{"dataName":"v16.jpg","dataSrc":"images/v16.jpg","fileType":"file","size":"5KB","children":[]},{"dataName":"v17.jpg","dataSrc":"images/v17.jpg","fileType":"file","size":"5KB","children":[]},{"dataName":"v18.jpg","dataSrc":"images/v18.jpg","fileType":"file","size":"3KB","children":[]},{"dataName":"v19.jpg","dataSrc":"images/v19.jpg","fileType":"file","size":"5KB","children":[]},{"dataName":"v2.jpg","dataSrc":"images/v2.jpg","fileType":"file","size":"4KB","children":[]},{"dataName":"v20.jpg","dataSrc":"images/v20.jpg","fileType":"file","size":"4KB","children":[]},{"dataName":"v21.jpg","dataSrc":"images/v21.jpg","fileType":"file","size":"4KB","children":[]},{"dataName":"v22.jpg","dataSrc":"images/v22.jpg","fileType":"file","size":"3KB","children":[]},{"dataName":"v23.jpg","dataSrc":"images/v23.jpg","fileType":"file","size":"5KB","children":[]},{"dataName":"v24.jpg","dataSrc":"images/v24.jpg","fileType":"file","size":"5KB","children":[]},{"dataName":"v25.jpg","dataSrc":"images/v25.jpg","fileType":"file","size":"6KB","children":[]},{"dataName":"v26.jpg","dataSrc":"images/v26.jpg","fileType":"file","size":"6KB","children":[]},{"dataName":"v27.jpg","dataSrc":"images/v27.jpg","fileType":"file","size":"5KB","children":[]},{"dataName":"v28.jpg","dataSrc":"images/v28.jpg","fileType":"file","size":"4KB","children":[]},{"dataName":"v3.jpg","dataSrc":"images/v3.jpg","fileType":"file","size":"5KB","children":[]},{"dataName":"v4.jpg","dataSrc":"images/v4.jpg","fileType":"file","size":"4KB","children":[]},{"dataName":"v5.jpg","dataSrc":"images/v5.jpg","fileType":"file","size":"4KB","children":[]},{"dataName":"v6.jpg","dataSrc":"images/v6.jpg","fileType":"file","size":"5KB","children":[]},{"dataName":"v7.jpg","dataSrc":"images/v7.jpg","fileType":"file","size":"5KB","children":[]},{"dataName":"v8.jpg","dataSrc":"images/v8.jpg","fileType":"file","size":"6KB","children":[]},{"dataName":"v9.jpg","dataSrc":"images/v9.jpg","fileType":"file","size":"6KB","children":[]}]},{"dataName":"index.html","dataSrc":"index.html","fileType":"file","size":"32KB","children":[]},{"dataName":"js","dataSrc":"js","fileType":"folder","size":"","children":[{"dataName":"foot.js","dataSrc":"js/foot.js","fileType":"file","size":"4KB","children":[]},{"dataName":"index.js","dataSrc":"js/index.js","fileType":"file","size":"13KB","children":[]},{"dataName":"jquery-1.7.2.min.js","dataSrc":"js/jquery-1.7.2.min.js","fileType":"file","size":"93KB","children":[]},{"dataName":"loadjs.js","dataSrc":"js/loadjs.js","fileType":"file","size":"2KB","children":[]},{"dataName":"milo.js","dataSrc":"js/milo.js","fileType":"file","size":"63KB","children":[]},{"dataName":"oss_base.js","dataSrc":"js/oss_base.js","fileType":"file","size":"31KB","children":[]},{"dataName":"reporting.js","dataSrc":"js/reporting.js","fileType":"file","size":"15KB","children":[]},{"dataName":"ticket.js","dataSrc":"js/ticket.js","fileType":"file","size":"10KB","children":[]},{"dataName":"x5_server_select.js","dataSrc":"js/x5_server_select.js","fileType":"file","size":"10KB","children":[]},{"dataName":"x5_top_201007.js","dataSrc":"js/x5_top_201007.js","fileType":"file","size":"3KB","children":[]}]},{"dataName":"_menu.json","dataSrc":"_menu.json","fileType":"file","size":"1KB","children":[]},{"dataName":"css","dataSrc":"css","fileType":"folder","size":"","children":[{"dataName":".DS_Store","dataSrc":"css/.DS_Store","fileType":"file","size":"7KB","children":[]},{"dataName":"animate.css","dataSrc":"css/animate.css","fileType":"file","size":"70KB","children":[]},{"dataName":"bootstrap-datetimepicker.min.css","dataSrc":"css/bootstrap-datetimepicker.min.css","fileType":"file","size":"8KB","children":[]},{"dataName":"bootstrap.css","dataSrc":"css/bootstrap.css","fileType":"file","size":"146KB","children":[]},{"dataName":"bootstrap.css.map","dataSrc":"css/bootstrap.css.map","fileType":"file","size":"84KB","children":[]},{"dataName":"flexslider.css","dataSrc":"css/flexslider.css","fileType":"file","size":"7KB","children":[]},{"dataName":"icomoon.css","dataSrc":"css/icomoon.css","fileType":"file","size":"37KB","children":[]},{"dataName":"simple-line-icons.css","dataSrc":"css/simple-line-icons.css","fileType":"file","size":"13KB","children":[]},{"dataName":"style.css","dataSrc":"css/style.css","fileType":"file","size":"32KB","children":[]},{"dataName":"style.css.map","dataSrc":"css/style.css.map","fileType":"file","size":"20KB","children":[]}]},{"dataName":"fonts","dataSrc":"fonts","fileType":"folder","size":"","children":[{"dataName":".DS_Store","dataSrc":"fonts/.DS_Store","fileType":"file","size":"7KB","children":[]},{"dataName":"bootstrap","dataSrc":"fonts/bootstrap","fileType":"folder","size":"","children":[{"dataName":"glyphicons-halflings-regular.eot","dataSrc":"fonts/bootstrap/glyphicons-halflings-regular.eot","fileType":"file","size":"20KB","children":[]},{"dataName":"glyphicons-halflings-regular.svg","dataSrc":"fonts/bootstrap/glyphicons-halflings-regular.svg","fileType":"file","size":"107KB","children":[]},{"dataName":"glyphicons-halflings-regular.ttf","dataSrc":"fonts/bootstrap/glyphicons-halflings-regular.ttf","fileType":"file","size":"45KB","children":[]},{"dataName":"glyphicons-halflings-regular.woff","dataSrc":"fonts/bootstrap/glyphicons-halflings-regular.woff","fileType":"file","size":"23KB","children":[]},{"dataName":"glyphicons-halflings-regular.woff2","dataSrc":"fonts/bootstrap/glyphicons-halflings-regular.woff2","fileType":"file","size":"18KB","children":[]}]},{"dataName":"icomoon","dataSrc":"fonts/icomoon","fileType":"folder","size":"","children":[{"dataName":".DS_Store","dataSrc":"fonts/icomoon/.DS_Store","fileType":"file","size":"7KB","children":[]},{"dataName":"icomoon","dataSrc":"fonts/icomoon/icomoon","fileType":"folder","size":"","children":[{"dataName":".DS_Store","dataSrc":"fonts/icomoon/icomoon/.DS_Store","fileType":"file","size":"7KB","children":[]},{"dataName":"demo-files","dataSrc":"fonts/icomoon/icomoon/demo-files","fileType":"folder","size":"","children":[{"dataName":"demo.css","dataSrc":"fonts/icomoon/icomoon/demo-files/demo.css","fileType":"file","size":"2KB","children":[]},{"dataName":"demo.js","dataSrc":"fonts/icomoon/icomoon/demo-files/demo.js","fileType":"file","size":"1KB","children":[]}]},{"dataName":"demo.html","dataSrc":"fonts/icomoon/icomoon/demo.html","fileType":"file","size":"474KB","children":[]},{"dataName":"fonts","dataSrc":"fonts/icomoon/icomoon/fonts","fileType":"folder","size":"","children":[{"dataName":"icomoon.eot","dataSrc":"fonts/icomoon/icomoon/fonts/icomoon.eot","fileType":"file","size":"196KB","children":[]},{"dataName":"icomoon.svg","dataSrc":"fonts/icomoon/icomoon/fonts/icomoon.svg","fileType":"file","size":"638KB","children":[]},{"dataName":"icomoon.ttf","dataSrc":"fonts/icomoon/icomoon/fonts/icomoon.ttf","fileType":"file","size":"196KB","children":[]},{"dataName":"icomoon.woff","dataSrc":"fonts/icomoon/icomoon/fonts/icomoon.woff","fileType":"file","size":"196KB","children":[]}]},{"dataName":"Read Me.txt","dataSrc":"fonts/icomoon/icomoon/Read Me.txt","fileType":"file","size":"1KB","children":[]},{"dataName":"selection.json","dataSrc":"fonts/icomoon/icomoon/selection.json","fileType":"file","size":"858KB","children":[]},{"dataName":"style.css","dataSrc":"fonts/icomoon/icomoon/style.css","fileType":"file","size":"37KB","children":[]}]},{"dataName":"icomoon.eot","dataSrc":"fonts/icomoon/icomoon.eot","fileType":"file","size":"196KB","children":[]},{"dataName":"icomoon.svg","dataSrc":"fonts/icomoon/icomoon.svg","fileType":"file","size":"638KB","children":[]},{"dataName":"icomoon.ttf","dataSrc":"fonts/icomoon/icomoon.ttf","fileType":"file","size":"196KB","children":[]},{"dataName":"icomoon.woff","dataSrc":"fonts/icomoon/icomoon.woff","fileType":"file","size":"196KB","children":[]}]},{"dataName":"simple-line-icons","dataSrc":"fonts/simple-line-icons","fileType":"folder","size":"","children":[{"dataName":"Simple-Line-Icons.eot","dataSrc":"fonts/simple-line-icons/Simple-Line-Icons.eot","fileType":"file","size":"53KB","children":[]},{"dataName":"Simple-Line-Icons.svg","dataSrc":"fonts/simple-line-icons/Simple-Line-Icons.svg","fileType":"file","size":"193KB","children":[]},{"dataName":"Simple-Line-Icons.ttf","dataSrc":"fonts/simple-line-icons/Simple-Line-Icons.ttf","fileType":"file","size":"53KB","children":[]},{"dataName":"Simple-Line-Icons.woff","dataSrc":"fonts/simple-line-icons/Simple-Line-Icons.woff","fileType":"file","size":"53KB","children":[]},{"dataName":"Simple-Line-Icons.woff2","dataSrc":"fonts/simple-line-icons/Simple-Line-Icons.woff2","fileType":"file","size":"26KB","children":[]}]}]},{"dataName":"images","dataSrc":"images","fileType":"folder","size":"","children":[{"dataName":".DS_Store","dataSrc":"images/.DS_Store","fileType":"file","size":"7KB","children":[]},{"dataName":"0103-served-plate_128.png","dataSrc":"images/0103-served-plate_128.png","fileType":"file","size":"5KB","children":[]},{"dataName":"0103-served-plate_64.png","dataSrc":"images/0103-served-plate_64.png","fileType":"file","size":"9KB","children":[]},{"dataName":"0203-coffee-love.png","dataSrc":"images/0203-coffee-love.png","fileType":"file","size":"4KB","children":[]},{"dataName":"0301-pina-colada.png","dataSrc":"images/0301-pina-colada.png","fileType":"file","size":"4KB","children":[]},{"dataName":"0301-pina-colada_64.png","dataSrc":"images/0301-pina-colada_64.png","fileType":"file","size":"4KB","children":[]},{"dataName":"0302-steak.png","dataSrc":"images/0302-steak.png","fileType":"file","size":"4KB","children":[]},{"dataName":"0401-vegan.png","dataSrc":"images/0401-vegan.png","fileType":"file","size":"4KB","children":[]},{"dataName":"0402-chef.png","dataSrc":"images/0402-chef.png","fileType":"file","size":"4KB","children":[]},{"dataName":"end.jpg","dataSrc":"images/end.jpg","fileType":"file","size":"42KB","children":[]},{"dataName":"loader.gif","dataSrc":"images/loader.gif","fileType":"file","size":"10KB","children":[]},{"dataName":"res_img_1.jpg","dataSrc":"images/res_img_1.jpg","fileType":"file","size":"44KB","children":[]},{"dataName":"res_img_2.jpg","dataSrc":"images/res_img_2.jpg","fileType":"file","size":"52KB","children":[]},{"dataName":"res_img_3.jpg","dataSrc":"images/res_img_3.jpg","fileType":"file","size":"7KB","children":[]},{"dataName":"res_img_4.jpg","dataSrc":"images/res_img_4.jpg","fileType":"file","size":"35KB","children":[]},{"dataName":"res_img_5.jpg","dataSrc":"images/res_img_5.jpg","fileType":"file","size":"41KB","children":[]},{"dataName":"res_img_6.jpg","dataSrc":"images/res_img_6.jpg","fileType":"file","size":"36KB","children":[]},{"dataName":"res_img_7.jpg","dataSrc":"images/res_img_7.jpg","fileType":"file","size":"26KB","children":[]},{"dataName":"res_img_8.jpg","dataSrc":"images/res_img_8.jpg","fileType":"file","size":"10KB","children":[]},{"dataName":"slide_1.jpg","dataSrc":"images/slide_1.jpg","fileType":"file","size":"118KB","children":[]},{"dataName":"slide_2.jpg","dataSrc":"images/slide_2.jpg","fileType":"file","size":"86KB","children":[]},{"dataName":"slide_3.jpg","dataSrc":"images/slide_3.jpg","fileType":"file","size":"92KB","children":[]},{"dataName":"type-1.png","dataSrc":"images/type-1.png","fileType":"file","size":"2KB","children":[]},{"dataName":"type-2.png","dataSrc":"images/type-2.png","fileType":"file","size":"2KB","children":[]},{"dataName":"type-3.png","dataSrc":"images/type-3.png","fileType":"file","size":"3KB","children":[]},{"dataName":"type-4.png","dataSrc":"images/type-4.png","fileType":"file","size":"2KB","children":[]},{"dataName":"wood_1.png","dataSrc":"images/wood_1.png","fileType":"file","size":"615KB","children":[]}]},{"dataName":"imgs","dataSrc":"imgs","fileType":"folder","size":"","children":[]},{"dataName":"index.html","dataSrc":"index.html","fileType":"file","size":"13KB","children":[]},{"dataName":"js","dataSrc":"js","fileType":"folder","size":"","children":[{"dataName":".DS_Store","dataSrc":"js/.DS_Store","fileType":"file","size":"7KB","children":[]},{"dataName":"bootstrap-datetimepicker.min.js","dataSrc":"js/bootstrap-datetimepicker.min.js","fileType":"file","size":"38KB","children":[]},{"dataName":"bootstrap.min.js","dataSrc":"js/bootstrap.min.js","fileType":"file","size":"36KB","children":[]},{"dataName":"jquery.easing.1.3.js","dataSrc":"js/jquery.easing.1.3.js","fileType":"file","size":"8KB","children":[]},{"dataName":"jquery.flexslider-min.js","dataSrc":"js/jquery.flexslider-min.js","fileType":"file","size":"22KB","children":[]},{"dataName":"jquery.min.js","dataSrc":"js/jquery.min.js","fileType":"file","size":"83KB","children":[]},{"dataName":"jquery.stellar.min.js","dataSrc":"js/jquery.stellar.min.js","fileType":"file","size":"13KB","children":[]},{"dataName":"jquery.waypoints.min.js","dataSrc":"js/jquery.waypoints.min.js","fileType":"file","size":"9KB","children":[]},{"dataName":"main.js","dataSrc":"js/main.js","fileType":"file","size":"13KB","children":[]},{"dataName":"modernizr-2.6.2.min.js","dataSrc":"js/modernizr-2.6.2.min.js","fileType":"file","size":"16KB","children":[]},{"dataName":"moment.js","dataSrc":"js/moment.js","fileType":"file","size":"117KB","children":[]},{"dataName":"respond.min.js","dataSrc":"js/respond.min.js","fileType":"file","size":"5KB","children":[]}]},{"dataName":"_menu.json","dataSrc":"_menu.json","fileType":"file","size":"1KB","children":[]},{"dataName":"css","dataSrc":"css","fileType":"folder","size":"","children":[{"dataName":"core.css","dataSrc":"css/core.css","fileType":"file","size":"37KB","children":[]}]},{"dataName":"fonts","dataSrc":"fonts","fileType":"folder","size":"","children":[{"dataName":"icomoon-yunxin.eot","dataSrc":"fonts/icomoon-yunxin.eot","fileType":"file","size":"21KB","children":[]},{"dataName":"icomoon-yunxin.svg","dataSrc":"fonts/icomoon-yunxin.svg","fileType":"file","size":"82KB","children":[]},{"dataName":"icomoon-yunxin.ttf","dataSrc":"fonts/icomoon-yunxin.ttf","fileType":"file","size":"21KB","children":[]},{"dataName":"icomoon-yunxin.woff","dataSrc":"fonts/icomoon-yunxin.woff","fileType":"file","size":"21KB","children":[]},{"dataName":"yH5BAEAAAAALAAAAAABAAEAAAIBRAA7","dataSrc":"fonts/yH5BAEAAAAALAAAAAABAAEAAAIBRAA7","fileType":"file","size":"1KB","children":[]}]},{"dataName":"images","dataSrc":"images","fileType":"folder","size":"","children":[{"dataName":"back-to-top-hover.png","dataSrc":"images/back-to-top-hover.png","fileType":"file","size":"1KB","children":[]},{"dataName":"back-to-top.png","dataSrc":"images/back-to-top.png","fileType":"file","size":"1KB","children":[]},{"dataName":"bg.jpg","dataSrc":"images/bg.jpg","fileType":"file","size":"9KB","children":[]},{"dataName":"bg_1.jpg","dataSrc":"images/bg_1.jpg","fileType":"file","size":"151KB","children":[]},{"dataName":"bg_2.jpg","dataSrc":"images/bg_2.jpg","fileType":"file","size":"131KB","children":[]},{"dataName":"bigtitle.png","dataSrc":"images/bigtitle.png","fileType":"file","size":"70KB","children":[]},{"dataName":"btn_home.png","dataSrc":"images/btn_home.png","fileType":"file","size":"2KB","children":[]},{"dataName":"btn_ljzx.png","dataSrc":"images/btn_ljzx.png","fileType":"file","size":"2KB","children":[]},{"dataName":"btn_qg.png","dataSrc":"images/btn_qg.png","fileType":"file","size":"3KB","children":[]},{"dataName":"bubble-consult.png","dataSrc":"images/bubble-consult.png","fileType":"file","size":"2KB","children":[]},{"dataName":"bubble-tel.png","dataSrc":"images/bubble-tel.png","fileType":"file","size":"2KB","children":[]},{"dataName":"cont.png","dataSrc":"images/cont.png","fileType":"file","size":"132KB","children":[]},{"dataName":"csa-star-logo-hover.png","dataSrc":"images/csa-star-logo-hover.png","fileType":"file","size":"4KB","children":[]},{"dataName":"csa-star-logo.png","dataSrc":"images/csa-star-logo.png","fileType":"file","size":"3KB","children":[]},{"dataName":"egg.png","dataSrc":"images/egg.png","fileType":"file","size":"83KB","children":[]},{"dataName":"float_nav.png","dataSrc":"images/float_nav.png","fileType":"file","size":"26KB","children":[]},{"dataName":"iso-cnas-logo-hover.png","dataSrc":"images/iso-cnas-logo-hover.png","fileType":"file","size":"3KB","children":[]},{"dataName":"iso-cnas-logo.png","dataSrc":"images/iso-cnas-logo.png","fileType":"file","size":"3KB","children":[]},{"dataName":"iso-ukas-logo-hover.png","dataSrc":"images/iso-ukas-logo-hover.png","fileType":"file","size":"4KB","children":[]},{"dataName":"iso-ukas-logo.png","dataSrc":"images/iso-ukas-logo.png","fileType":"file","size":"3KB","children":[]},{"dataName":"line.png","dataSrc":"images/line.png","fileType":"file","size":"2KB","children":[]},{"dataName":"mail_active.jpg","dataSrc":"images/mail_active.jpg","fileType":"file","size":"79KB","children":[]},{"dataName":"mail_inactive.jpg","dataSrc":"images/mail_inactive.jpg","fileType":"file","size":"60KB","children":[]},{"dataName":"new.png","dataSrc":"images/new.png","fileType":"file","size":"1KB","children":[]},{"dataName":"notice.png","dataSrc":"images/notice.png","fileType":"file","size":"2KB","children":[]},{"dataName":"private-icon.jpg","dataSrc":"images/private-icon.jpg","fileType":"file","size":"11KB","children":[]},{"dataName":"split-line.png","dataSrc":"images/split-line.png","fileType":"file","size":"2KB","children":[]},{"dataName":"tag2.png","dataSrc":"images/tag2.png","fileType":"file","size":"2KB","children":[]},{"dataName":"title.png","dataSrc":"images/title.png","fileType":"file","size":"19KB","children":[]},{"dataName":"yunxin-white@1x.png","dataSrc":"images/yunxin-white@1x.png","fileType":"file","size":"4KB","children":[]},{"dataName":"yunxin@2x.png","dataSrc":"images/yunxin@2x.png","fileType":"file","size":"7KB","children":[]}]},{"dataName":"index.html","dataSrc":"index.html","fileType":"file","size":"23KB","children":[]},{"dataName":"js","dataSrc":"js","fileType":"folder","size":"","children":[{"dataName":"axios.min.js","dataSrc":"js/axios.min.js","fileType":"file","size":"11KB","children":[]},{"dataName":"es6-promise.min.js","dataSrc":"js/es6-promise.min.js","fileType":"file","size":"7KB","children":[]},{"dataName":"pt_promotion_11.js","dataSrc":"js/pt_promotion_11.js","fileType":"file","size":"79KB","children":[]},{"dataName":"report.js","dataSrc":"js/report.js","fileType":"file","size":"3KB","children":[]}]},{"dataName":"_menu.json","dataSrc":"_menu.json","fileType":"file","size":"1KB","children":[]},{"dataName":"css","dataSrc":"css","fileType":"folder","size":"","children":[{"dataName":"css.css","dataSrc":"css/css.css","fileType":"file","size":"47KB","children":[]}]},{"dataName":"images","dataSrc":"images","fileType":"folder","size":"","children":[{"dataName":"address.png","dataSrc":"images/address.png","fileType":"file","size":"5KB","children":[]},{"dataName":"bac1.jpg","dataSrc":"images/bac1.jpg","fileType":"file","size":"153KB","children":[]},{"dataName":"bac2.jpg","dataSrc":"images/bac2.jpg","fileType":"file","size":"221KB","children":[]},{"dataName":"bac3.jpg","dataSrc":"images/bac3.jpg","fileType":"file","size":"214KB","children":[]},{"dataName":"banner1.png","dataSrc":"images/banner1.png","fileType":"file","size":"28KB","children":[]},{"dataName":"banner1_h5.png","dataSrc":"images/banner1_h5.png","fileType":"file","size":"3KB","children":[]},{"dataName":"bjdx.png","dataSrc":"images/bjdx.png","fileType":"file","size":"32KB","children":[]},{"dataName":"case01.jpg","dataSrc":"images/case01.jpg","fileType":"file","size":"47KB","children":[]},{"dataName":"case02.jpg","dataSrc":"images/case02.jpg","fileType":"file","size":"32KB","children":[]},{"dataName":"case03.jpg","dataSrc":"images/case03.jpg","fileType":"file","size":"32KB","children":[]},{"dataName":"caseimg.jpg","dataSrc":"images/caseimg.jpg","fileType":"file","size":"3691KB","children":[]},{"dataName":"caselogo.png","dataSrc":"images/caselogo.png","fileType":"file","size":"5KB","children":[]},{"dataName":"connect.png","dataSrc":"images/connect.png","fileType":"file","size":"5KB","children":[]},{"dataName":"cont.png","dataSrc":"images/cont.png","fileType":"file","size":"6KB","children":[]},{"dataName":"cust.png","dataSrc":"images/cust.png","fileType":"file","size":"5KB","children":[]},{"dataName":"cust1.jpg","dataSrc":"images/cust1.jpg","fileType":"file","size":"6KB","children":[]},{"dataName":"cust10.jpg","dataSrc":"images/cust10.jpg","fileType":"file","size":"4KB","children":[]},{"dataName":"cust11.jpg","dataSrc":"images/cust11.jpg","fileType":"file","size":"6KB","children":[]},{"dataName":"cust12.jpg","dataSrc":"images/cust12.jpg","fileType":"file","size":"5KB","children":[]},{"dataName":"cust13.jpg","dataSrc":"images/cust13.jpg","fileType":"file","size":"4KB","children":[]},{"dataName":"cust14.jpg","dataSrc":"images/cust14.jpg","fileType":"file","size":"4KB","children":[]},{"dataName":"cust15.jpg","dataSrc":"images/cust15.jpg","fileType":"file","size":"4KB","children":[]},{"dataName":"cust2.jpg","dataSrc":"images/cust2.jpg","fileType":"file","size":"5KB","children":[]},{"dataName":"cust3.jpg","dataSrc":"images/cust3.jpg","fileType":"file","size":"4KB","children":[]},{"dataName":"cust4.jpg","dataSrc":"images/cust4.jpg","fileType":"file","size":"5KB","children":[]},{"dataName":"cust5.jpg","dataSrc":"images/cust5.jpg","fileType":"file","size":"4KB","children":[]},{"dataName":"cust6.jpg","dataSrc":"images/cust6.jpg","fileType":"file","size":"5KB","children":[]},{"dataName":"cust7.jpg","dataSrc":"images/cust7.jpg","fileType":"file","size":"6KB","children":[]},{"dataName":"cust8.jpg","dataSrc":"images/cust8.jpg","fileType":"file","size":"4KB","children":[]},{"dataName":"cust9.jpg","dataSrc":"images/cust9.jpg","fileType":"file","size":"4KB","children":[]},{"dataName":"diannao.png","dataSrc":"images/diannao.png","fileType":"file","size":"2KB","children":[]},{"dataName":"diannao1.png","dataSrc":"images/diannao1.png","fileType":"file","size":"2KB","children":[]},{"dataName":"dp.png","dataSrc":"images/dp.png","fileType":"file","size":"2KB","children":[]},{"dataName":"dp1.png","dataSrc":"images/dp1.png","fileType":"file","size":"2KB","children":[]},{"dataName":"email.png","dataSrc":"images/email.png","fileType":"file","size":"4KB","children":[]},{"dataName":"ewm.png","dataSrc":"images/ewm.png","fileType":"file","size":"10KB","children":[]},{"dataName":"fengxian.png","dataSrc":"images/fengxian.png","fileType":"file","size":"21KB","children":[]},{"dataName":"fk.png","dataSrc":"images/fk.png","fileType":"file","size":"2KB","children":[]},{"dataName":"headli1.png","dataSrc":"images/headli1.png","fileType":"file","size":"48KB","children":[]},{"dataName":"hnav.png","dataSrc":"images/hnav.png","fileType":"file","size":"1KB","children":[]},{"dataName":"icons.png","dataSrc":"images/icons.png","fileType":"file","size":"4KB","children":[]},{"dataName":"icons1.png","dataSrc":"images/icons1.png","fileType":"file","size":"2KB","children":[]},{"dataName":"jl.png","dataSrc":"images/jl.png","fileType":"file","size":"201KB","children":[]},{"dataName":"jl1.png","dataSrc":"images/jl1.png","fileType":"file","size":"48KB","children":[]},{"dataName":"lc.png","dataSrc":"images/lc.png","fileType":"file","size":"116KB","children":[]},{"dataName":"lc1.png","dataSrc":"images/lc1.png","fileType":"file","size":"64KB","children":[]},{"dataName":"libg1.jpg","dataSrc":"images/libg1.jpg","fileType":"file","size":"378KB","children":[]},{"dataName":"libg2.jpg","dataSrc":"images/libg2.jpg","fileType":"file","size":"107KB","children":[]},{"dataName":"libg3.jpg","dataSrc":"images/libg3.jpg","fileType":"file","size":"328KB","children":[]},{"dataName":"libg4.jpg","dataSrc":"images/libg4.jpg","fileType":"file","size":"120KB","children":[]},{"dataName":"listcase.jpg","dataSrc":"images/listcase.jpg","fileType":"file","size":"217KB","children":[]},{"dataName":"liulan.png","dataSrc":"images/liulan.png","fileType":"file","size":"2KB","children":[]},{"dataName":"logo.jpg","dataSrc":"images/logo.jpg","fileType":"file","size":"33KB","children":[]},{"dataName":"logo10.jpg","dataSrc":"images/logo10.jpg","fileType":"file","size":"33KB","children":[]},{"dataName":"logo11.jpg","dataSrc":"images/logo11.jpg","fileType":"file","size":"25KB","children":[]},{"dataName":"logo12.jpg","dataSrc":"images/logo12.jpg","fileType":"file","size":"21KB","children":[]},{"dataName":"logo13.jpg","dataSrc":"images/logo13.jpg","fileType":"file","size":"24KB","children":[]},{"dataName":"logo14.jpg","dataSrc":"images/logo14.jpg","fileType":"file","size":"23KB","children":[]},{"dataName":"logo15.jpg","dataSrc":"images/logo15.jpg","fileType":"file","size":"23KB","children":[]},{"dataName":"logo16.jpg","dataSrc":"images/logo16.jpg","fileType":"file","size":"22KB","children":[]},{"dataName":"logo17.jpg","dataSrc":"images/logo17.jpg","fileType":"file","size":"29KB","children":[]},{"dataName":"logo18.jpg","dataSrc":"images/logo18.jpg","fileType":"file","size":"28KB","children":[]},{"dataName":"logo19.jpg","dataSrc":"images/logo19.jpg","fileType":"file","size":"27KB","children":[]},{"dataName":"logo2.jpg","dataSrc":"images/logo2.jpg","fileType":"file","size":"33KB","children":[]},{"dataName":"logo2.png","dataSrc":"images/logo2.png","fileType":"file","size":"41KB","children":[]},{"dataName":"logo20.jpg","dataSrc":"images/logo20.jpg","fileType":"file","size":"23KB","children":[]},{"dataName":"logo3.jpg","dataSrc":"images/logo3.jpg","fileType":"file","size":"23KB","children":[]},{"dataName":"logo4.jpg","dataSrc":"images/logo4.jpg","fileType":"file","size":"35KB","children":[]},{"dataName":"logo5.jpg","dataSrc":"images/logo5.jpg","fileType":"file","size":"23KB","children":[]},{"dataName":"logo6.jpg","dataSrc":"images/logo6.jpg","fileType":"file","size":"24KB","children":[]},{"dataName":"logo7.jpg","dataSrc":"images/logo7.jpg","fileType":"file","size":"23KB","children":[]},{"dataName":"logo8.jpg","dataSrc":"images/logo8.jpg","fileType":"file","size":"25KB","children":[]},{"dataName":"logo9.jpg","dataSrc":"images/logo9.jpg","fileType":"file","size":"23KB","children":[]},{"dataName":"logob.png","dataSrc":"images/logob.png","fileType":"file","size":"4KB","children":[]},{"dataName":"logobf.png","dataSrc":"images/logobf.png","fileType":"file","size":"2KB","children":[]},{"dataName":"logow.png","dataSrc":"images/logow.png","fileType":"file","size":"4KB","children":[]},{"dataName":"logowf.png","dataSrc":"images/logowf.png","fileType":"file","size":"2KB","children":[]},{"dataName":"lqk.png","dataSrc":"images/lqk.png","fileType":"file","size":"202KB","children":[]},{"dataName":"lqk1.png","dataSrc":"images/lqk1.png","fileType":"file","size":"57KB","children":[]},{"dataName":"lw.png","dataSrc":"images/lw.png","fileType":"file","size":"202KB","children":[]},{"dataName":"lw1.png","dataSrc":"images/lw1.png","fileType":"file","size":"53KB","children":[]},{"dataName":"map.png","dataSrc":"images/map.png","fileType":"file","size":"48KB","children":[]},{"dataName":"meng.png","dataSrc":"images/meng.png","fileType":"file","size":"1KB","children":[]},{"dataName":"mouse.png","dataSrc":"images/mouse.png","fileType":"file","size":"2KB","children":[]},{"dataName":"mouse1.png","dataSrc":"images/mouse1.png","fileType":"file","size":"2KB","children":[]},{"dataName":"mouse3.png","dataSrc":"images/mouse3.png","fileType":"file","size":"2KB","children":[]},{"dataName":"mouse4.png","dataSrc":"images/mouse4.png","fileType":"file","size":"3KB","children":[]},{"dataName":"mouse5.png","dataSrc":"images/mouse5.png","fileType":"file","size":"2KB","children":[]},{"dataName":"myl.png","dataSrc":"images/myl.png","fileType":"file","size":"202KB","children":[]},{"dataName":"myl1.png","dataSrc":"images/myl1.png","fileType":"file","size":"55KB","children":[]},{"dataName":"news.png","dataSrc":"images/news.png","fileType":"file","size":"6KB","children":[]},{"dataName":"news1.jpg","dataSrc":"images/news1.jpg","fileType":"file","size":"28KB","children":[]},{"dataName":"news2.jpg","dataSrc":"images/news2.jpg","fileType":"file","size":"21KB","children":[]},{"dataName":"news3.jpg","dataSrc":"images/news3.jpg","fileType":"file","size":"14KB","children":[]},{"dataName":"news4.jpg","dataSrc":"images/news4.jpg","fileType":"file","size":"10KB","children":[]},{"dataName":"news5.jpg","dataSrc":"images/news5.jpg","fileType":"file","size":"22KB","children":[]},{"dataName":"newsheader_bg.jpg","dataSrc":"images/newsheader_bg.jpg","fileType":"file","size":"90KB","children":[]},{"dataName":"newslist1.jpg","dataSrc":"images/newslist1.jpg","fileType":"file","size":"16KB","children":[]},{"dataName":"newslist2.jpg","dataSrc":"images/newslist2.jpg","fileType":"file","size":"15KB","children":[]},{"dataName":"newslist3.jpg","dataSrc":"images/newslist3.jpg","fileType":"file","size":"16KB","children":[]},{"dataName":"newslist4.jpg","dataSrc":"images/newslist4.jpg","fileType":"file","size":"20KB","children":[]},{"dataName":"newslist5.jpg","dataSrc":"images/newslist5.jpg","fileType":"file","size":"19KB","children":[]},{"dataName":"newslist6.jpg","dataSrc":"images/newslist6.jpg","fileType":"file","size":"23KB","children":[]},{"dataName":"newslist7.jpg","dataSrc":"images/newslist7.jpg","fileType":"file","size":"20KB","children":[]},{"dataName":"next.png","dataSrc":"images/next.png","fileType":"file","size":"2KB","children":[]},{"dataName":"next1.png","dataSrc":"images/next1.png","fileType":"file","size":"2KB","children":[]},{"dataName":"num1_bg.jpg","dataSrc":"images/num1_bg.jpg","fileType":"file","size":"242KB","children":[]},{"dataName":"num2_bg.jpg","dataSrc":"images/num2_bg.jpg","fileType":"file","size":"114KB","children":[]},{"dataName":"num3_bg.jpg","dataSrc":"images/num3_bg.jpg","fileType":"file","size":"81KB","children":[]},{"dataName":"num4_bg.jpg","dataSrc":"images/num4_bg.jpg","fileType":"file","size":"106KB","children":[]},{"dataName":"num5_bg.jpg","dataSrc":"images/num5_bg.jpg","fileType":"file","size":"105KB","children":[]},{"dataName":"num6_bg.jpg","dataSrc":"images/num6_bg.jpg","fileType":"file","size":"194KB","children":[]},{"dataName":"num7_bg.jpg","dataSrc":"images/num7_bg.jpg","fileType":"file","size":"99KB","children":[]},{"dataName":"nut.jpg","dataSrc":"images/nut.jpg","fileType":"file","size":"111KB","children":[]},{"dataName":"nutt.png","dataSrc":"images/nutt.png","fileType":"file","size":"18KB","children":[]},{"dataName":"pagecase.jpg","dataSrc":"images/pagecase.jpg","fileType":"file","size":"2809KB","children":[]},{"dataName":"pagenews1.jpg","dataSrc":"images/pagenews1.jpg","fileType":"file","size":"54KB","children":[]},{"dataName":"pagenews2.jpg","dataSrc":"images/pagenews2.jpg","fileType":"file","size":"47KB","children":[]},{"dataName":"pagenews3.jpg","dataSrc":"images/pagenews3.jpg","fileType":"file","size":"59KB","children":[]},{"dataName":"pingban.png","dataSrc":"images/pingban.png","fileType":"file","size":"2KB","children":[]},{"dataName":"pingban1.png","dataSrc":"images/pingban1.png","fileType":"file","size":"2KB","children":[]},{"dataName":"prev.png","dataSrc":"images/prev.png","fileType":"file","size":"2KB","children":[]},{"dataName":"prev1.png","dataSrc":"images/prev1.png","fileType":"file","size":"2KB","children":[]},{"dataName":"serv.png","dataSrc":"images/serv.png","fileType":"file","size":"59KB","children":[]},{"dataName":"serv1.png","dataSrc":"images/serv1.png","fileType":"file","size":"84KB","children":[]},{"dataName":"serv2.png","dataSrc":"images/serv2.png","fileType":"file","size":"42KB","children":[]},{"dataName":"serv3.png","dataSrc":"images/serv3.png","fileType":"file","size":"60KB","children":[]},{"dataName":"serv4.png","dataSrc":"images/serv4.png","fileType":"file","size":"30KB","children":[]},{"dataName":"serv5.png","dataSrc":"images/serv5.png","fileType":"file","size":"89KB","children":[]},{"dataName":"six1.png","dataSrc":"images/six1.png","fileType":"file","size":"13KB","children":[]},{"dataName":"six1_old.png","dataSrc":"images/six1_old.png","fileType":"file","size":"13KB","children":[]},{"dataName":"six2.png","dataSrc":"images/six2.png","fileType":"file","size":"170KB","children":[]},{"dataName":"six2_old.png","dataSrc":"images/six2_old.png","fileType":"file","size":"170KB","children":[]},{"dataName":"team.png","dataSrc":"images/team.png","fileType":"file","size":"6KB","children":[]},{"dataName":"team1.png","dataSrc":"images/team1.png","fileType":"file","size":"26KB","children":[]},{"dataName":"team2.png","dataSrc":"images/team2.png","fileType":"file","size":"28KB","children":[]},{"dataName":"team3.png","dataSrc":"images/team3.png","fileType":"file","size":"19KB","children":[]},{"dataName":"team4.png","dataSrc":"images/team4.png","fileType":"file","size":"20KB","children":[]},{"dataName":"telb.png","dataSrc":"images/telb.png","fileType":"file","size":"3KB","children":[]},{"dataName":"telw.png","dataSrc":"images/telw.png","fileType":"file","size":"2KB","children":[]},{"dataName":"vip.png","dataSrc":"images/vip.png","fileType":"file","size":"3KB","children":[]},{"dataName":"vip1.png","dataSrc":"images/vip1.png","fileType":"file","size":"2KB","children":[]},{"dataName":"weixin.png","dataSrc":"images/weixin.png","fileType":"file","size":"4KB","children":[]},{"dataName":"weixin1.png","dataSrc":"images/weixin1.png","fileType":"file","size":"2KB","children":[]},{"dataName":"whq.png","dataSrc":"images/whq.png","fileType":"file","size":"202KB","children":[]},{"dataName":"whq1.png","dataSrc":"images/whq1.png","fileType":"file","size":"55KB","children":[]},{"dataName":"xfanniu1.png","dataSrc":"images/xfanniu1.png","fileType":"file","size":"2KB","children":[]},{"dataName":"xfbg.png","dataSrc":"images/xfbg.png","fileType":"file","size":"2KB","children":[]},{"dataName":"xfbg2.png","dataSrc":"images/xfbg2.png","fileType":"file","size":"2KB","children":[]},{"dataName":"xfbg3.png","dataSrc":"images/xfbg3.png","fileType":"file","size":"2KB","children":[]},{"dataName":"xftb1.png","dataSrc":"images/xftb1.png","fileType":"file","size":"2KB","children":[]},{"dataName":"xftb2.png","dataSrc":"images/xftb2.png","fileType":"file","size":"2KB","children":[]},{"dataName":"xftb3.png","dataSrc":"images/xftb3.png","fileType":"file","size":"2KB","children":[]},{"dataName":"xftb4.png","dataSrc":"images/xftb4.png","fileType":"file","size":"2KB","children":[]},{"dataName":"xm.png","dataSrc":"images/xm.png","fileType":"file","size":"198KB","children":[]},{"dataName":"xm1.png","dataSrc":"images/xm1.png","fileType":"file","size":"49KB","children":[]},{"dataName":"yjl.png","dataSrc":"images/yjl.png","fileType":"file","size":"202KB","children":[]},{"dataName":"yjl1.png","dataSrc":"images/yjl1.png","fileType":"file","size":"56KB","children":[]},{"dataName":"zhuti.png","dataSrc":"images/zhuti.png","fileType":"file","size":"18KB","children":[]},{"dataName":"zuozhe.png","dataSrc":"images/zuozhe.png","fileType":"file","size":"2KB","children":[]},{"dataName":"zwn.png","dataSrc":"images/zwn.png","fileType":"file","size":"201KB","children":[]},{"dataName":"zwn1.png","dataSrc":"images/zwn1.png","fileType":"file","size":"44KB","children":[]},{"dataName":"zzz.png","dataSrc":"images/zzz.png","fileType":"file","size":"202KB","children":[]},{"dataName":"zzz1.png","dataSrc":"images/zzz1.png","fileType":"file","size":"58KB","children":[]}]},{"dataName":"img","dataSrc":"img","fileType":"folder","size":"","children":[{"dataName":"1.jpg","dataSrc":"img/1.jpg","fileType":"file","size":"4KB","children":[]},{"dataName":"10.jpg","dataSrc":"img/10.jpg","fileType":"file","size":"8KB","children":[]},{"dataName":"11.jpg","dataSrc":"img/11.jpg","fileType":"file","size":"9KB","children":[]},{"dataName":"12.jpg","dataSrc":"img/12.jpg","fileType":"file","size":"4KB","children":[]},{"dataName":"13.jpg","dataSrc":"img/13.jpg","fileType":"file","size":"9KB","children":[]},{"dataName":"14.jpg","dataSrc":"img/14.jpg","fileType":"file","size":"6KB","children":[]},{"dataName":"15.jpg","dataSrc":"img/15.jpg","fileType":"file","size":"9KB","children":[]},{"dataName":"16.jpg","dataSrc":"img/16.jpg","fileType":"file","size":"5KB","children":[]},{"dataName":"17.jpg","dataSrc":"img/17.jpg","fileType":"file","size":"8KB","children":[]},{"dataName":"18.jpg","dataSrc":"img/18.jpg","fileType":"file","size":"5KB","children":[]},{"dataName":"19.jpg","dataSrc":"img/19.jpg","fileType":"file","size":"3KB","children":[]},{"dataName":"2.jpg","dataSrc":"img/2.jpg","fileType":"file","size":"7KB","children":[]},{"dataName":"20.jpg","dataSrc":"img/20.jpg","fileType":"file","size":"6KB","children":[]},{"dataName":"21.jpg","dataSrc":"img/21.jpg","fileType":"file","size":"7KB","children":[]},{"dataName":"22.jpg","dataSrc":"img/22.jpg","fileType":"file","size":"10KB","children":[]},{"dataName":"23.jpg","dataSrc":"img/23.jpg","fileType":"file","size":"9KB","children":[]},{"dataName":"24.jpg","dataSrc":"img/24.jpg","fileType":"file","size":"4KB","children":[]},{"dataName":"25.jpg","dataSrc":"img/25.jpg","fileType":"file","size":"3KB","children":[]},{"dataName":"26.jpg","dataSrc":"img/26.jpg","fileType":"file","size":"4KB","children":[]},{"dataName":"27.jpg","dataSrc":"img/27.jpg","fileType":"file","size":"9KB","children":[]},{"dataName":"28.jpg","dataSrc":"img/28.jpg","fileType":"file","size":"6KB","children":[]},{"dataName":"29.jpg","dataSrc":"img/29.jpg","fileType":"file","size":"13KB","children":[]},{"dataName":"3.jpg","dataSrc":"img/3.jpg","fileType":"file","size":"2KB","children":[]},{"dataName":"30.jpg","dataSrc":"img/30.jpg","fileType":"file","size":"5KB","children":[]},{"dataName":"31.jpg","dataSrc":"img/31.jpg","fileType":"file","size":"5KB","children":[]},{"dataName":"32.jpg","dataSrc":"img/32.jpg","fileType":"file","size":"6KB","children":[]},{"dataName":"33.jpg","dataSrc":"img/33.jpg","fileType":"file","size":"6KB","children":[]},{"dataName":"34.jpg","dataSrc":"img/34.jpg","fileType":"file","size":"6KB","children":[]},{"dataName":"35.jpg","dataSrc":"img/35.jpg","fileType":"file","size":"5KB","children":[]},{"dataName":"36.jpg","dataSrc":"img/36.jpg","fileType":"file","size":"6KB","children":[]},{"dataName":"37.jpg","dataSrc":"img/37.jpg","fileType":"file","size":"9KB","children":[]},{"dataName":"38.jpg","dataSrc":"img/38.jpg","fileType":"file","size":"3KB","children":[]},{"dataName":"39.jpg","dataSrc":"img/39.jpg","fileType":"file","size":"10KB","children":[]},{"dataName":"4.jpg","dataSrc":"img/4.jpg","fileType":"file","size":"9KB","children":[]},{"dataName":"40.jpg","dataSrc":"img/40.jpg","fileType":"file","size":"8KB","children":[]},{"dataName":"41.jpg","dataSrc":"img/41.jpg","fileType":"file","size":"8KB","children":[]},{"dataName":"42.jpg","dataSrc":"img/42.jpg","fileType":"file","size":"7KB","children":[]},{"dataName":"43.jpg","dataSrc":"img/43.jpg","fileType":"file","size":"3KB","children":[]},{"dataName":"44.jpg","dataSrc":"img/44.jpg","fileType":"file","size":"4KB","children":[]},{"dataName":"45.jpg","dataSrc":"img/45.jpg","fileType":"file","size":"4KB","children":[]},{"dataName":"46.jpg","dataSrc":"img/46.jpg","fileType":"file","size":"12KB","children":[]},{"dataName":"47.jpg","dataSrc":"img/47.jpg","fileType":"file","size":"4KB","children":[]},{"dataName":"48.jpg","dataSrc":"img/48.jpg","fileType":"file","size":"6KB","children":[]},{"dataName":"49.jpg","dataSrc":"img/49.jpg","fileType":"file","size":"6KB","children":[]},{"dataName":"5.jpg","dataSrc":"img/5.jpg","fileType":"file","size":"12KB","children":[]},{"dataName":"50.jpg","dataSrc":"img/50.jpg","fileType":"file","size":"5KB","children":[]},{"dataName":"6.jpg","dataSrc":"img/6.jpg","fileType":"file","size":"7KB","children":[]},{"dataName":"7.jpg","dataSrc":"img/7.jpg","fileType":"file","size":"7KB","children":[]},{"dataName":"8.jpg","dataSrc":"img/8.jpg","fileType":"file","size":"4KB","children":[]},{"dataName":"9.jpg","dataSrc":"img/9.jpg","fileType":"file","size":"6KB","children":[]}]},{"dataName":"index.html","dataSrc":"index.html","fileType":"file","size":"48KB","children":[]},{"dataName":"js","dataSrc":"js","fileType":"folder","size":"","children":[{"dataName":"banner-1.js","dataSrc":"js/banner-1.js","fileType":"file","size":"6KB","children":[]},{"dataName":"gundong.js","dataSrc":"js/gundong.js","fileType":"file","size":"3KB","children":[]},{"dataName":"gundong1.js","dataSrc":"js/gundong1.js","fileType":"file","size":"4KB","children":[]},{"dataName":"jquery-1.11.1.js","dataSrc":"js/jquery-1.11.1.js","fileType":"file","size":"277KB","children":[]},{"dataName":"jquery-1.8.2.min.js","dataSrc":"js/jquery-1.8.2.min.js","fileType":"file","size":"92KB","children":[]},{"dataName":"jquery.easing.min.js","dataSrc":"js/jquery.easing.min.js","fileType":"file","size":"6KB","children":[]},{"dataName":"jquery.mousewheel.js","dataSrc":"js/jquery.mousewheel.js","fileType":"file","size":"8KB","children":[]},{"dataName":"jquery.SuperSlide.2.1.1.js","dataSrc":"js/jquery.SuperSlide.2.1.1.js","fileType":"file","size":"11KB","children":[]},{"dataName":"js.js","dataSrc":"js/js.js","fileType":"file","size":"4KB","children":[]},{"dataName":"scroll.js","dataSrc":"js/scroll.js","fileType":"file","size":"19KB","children":[]},{"dataName":"ss.js","dataSrc":"js/ss.js","fileType":"file","size":"9KB","children":[]},{"dataName":"switch.js","dataSrc":"js/switch.js","fileType":"file","size":"5KB","children":[]}]},{"dataName":"_menu.json","dataSrc":"_menu.json","fileType":"file","size":"1KB","children":[]}]}